{
  "Pad": {
    "TotalYcCount": 3,
    "TotalYxCount": 10,
    "TotalYkCount": 2,
    "TotalDDCount": 0,
    "TotalParameterCount": 0,
    "YcRatioEnable": 1,
    "RecordingYkOpera": 0,
    "LinkAddr": 1,
    "SingleORDoubleInit": 0,
    "LinkAddrLen": 2,
    "VsqLen": 1,
    "coTlen": 2,
    "AsduLen": 2,
    "InfoAddrLen": 3,
    "YxType": 1,
    "YcType": 13,
    "DdType": 206,
    "YkType": 45,
    "T0TimeOut": 30,
    "T1TimeOut": 30,
    "T2TimeOut": 12,
    "T3TimeOut": 20,
    "k": 12,
    "w": 8,
    "baseyear": 2000,
    "alldatainterval": 0,
    "allddinterval": 0,
    "setclockinterval": 0,
    "testlinkinterval": 0,
    "encrypt": 0,
    "sendcos": 1,
    "BackScan": 0,
    "ThreadAfterSndDelayms": 100,
    "ThreadAfterRcvDelayms": 100
  },
  "ParaInstruction": "v0.1运用园区",
  "Para": [
    {
      "SN": 0,
      "Running_info": [
        {
          "No": 1,
          "Addr": 32800,
          "Desc": "modbus通用函数发帧函数",
          "Unit": "整形4字节",
          "Type": 2,
          "MapAddr": 2
        },
        {
          "No": 2,
          "Addr": 32801,
          "Desc": "modbus通用函数发帧函数",
          "Unit": "整形4字节",
          "Type": 2,
          "MapAddr": 2
        },
        {
          "No": 3,
          "Addr": 32802,
          "Desc": "modbus通用函数发帧函数",
          "Unit": "整形4字节",
          "Type": 2,
          "MapAddr": 2
        },
        {
          "No": 4,
          "Addr": 32803,
          "Desc": "逆变器方阵调节（并网调节）",
          "Unit": "float4字节",
          "Type": 38,
          "MapAddr": 8
        }
      ],
      "Actionfixed_info": []
    }
  ],
  "FaultEventSubmission": [],
  "YCDataItem": [
    {
      "No": 0,
      "Name": "设备[0]-A相电压-断路器-实时库号[596]",
      "Unit": null,
      "Addr": 16385,
      "Xishu": 1.0,
      "RealDevNo": 596,
      "type": 1,
      "CurrentValue": 0.0,
      "Idx": 0
    },
    {
      "No": 1,
      "Name": "设备[0]-B相电压-断路器-实时库号[597]",
      "Unit": null,
      "Addr": 16386,
      "Xishu": 1.0,
      "RealDevNo": 597,
      "type": 1,
      "CurrentValue": 0.0,
      "Idx": 1
    },
    {
      "No": 2,
      "Name": "设备[0]-C相电压-断路器-实时库号[598]",
      "Unit": null,
      "Addr": 16387,
      "Xishu": 1.0,
      "RealDevNo": 598,
      "type": 1,
      "CurrentValue": 0.0,
      "Idx": 2
    }
  ],
  "YXDataItem": [
    {
      "No": 0,
      "Name": "设备[0]-过压告警/保护-实时库号[183]",
      "Unit": null,
      "Addr": 1,
      "Xishu": 1.0,
      "RealDevNo": 183,
      "type": 0,
      "CurrentValue": 0.0,
      "Idx": 0
    },
    {
      "No": 1,
      "Name": "设备[0]-欠压告警/保护-实时库号[191]",
      "Unit": null,
      "Addr": 2,
      "Xishu": 1.0,
      "RealDevNo": 191,
      "type": 0,
      "CurrentValue": 0.0,
      "Idx": 1
    },
    {
      "No": 2,
      "Name": "设备[0]-过频告警/保护-实时库号[227]",
      "Unit": null,
      "Addr": 3,
      "Xishu": 1.0,
      "RealDevNo": 227,
      "type": 0,
      "CurrentValue": 0.0,
      "Idx": 2
    },
    {
      "No": 3,
      "Name": "设备[0]-失频告警/保护-实时库号[235]",
      "Unit": null,
      "Addr": 4,
      "Xishu": 1.0,
      "RealDevNo": 235,
      "type": 0,
      "CurrentValue": 0.0,
      "Idx": 3
    },
    {
      "No": 4,
      "Name": "设备[0]-电流不平衡告警/保护-实时库号[217]",
      "Unit": null,
      "Addr": 5,
      "Xishu": 1.0,
      "RealDevNo": 217,
      "type": 0,
      "CurrentValue": 0.0,
      "Idx": 4
    },
    {
      "No": 5,
      "Name": "设备[0]-电压不平衡告警/保护-实时库号[215]",
      "Unit": null,
      "Addr": 6,
      "Xishu": 1.0,
      "RealDevNo": 215,
      "type": 0,
      "CurrentValue": 0.0,
      "Idx": 5
    },
    {
      "No": 6,
      "Name": "设备[0]-过流告警/保护-实时库号[199]",
      "Unit": null,
      "Addr": 7,
      "Xishu": 1.0,
      "RealDevNo": 199,
      "type": 0,
      "CurrentValue": 0.0,
      "Idx": 6
    },
    {
      "No": 7,
      "Name": "设备[0]-并网发电-实时库号[500]",
      "Unit": null,
      "Addr": 8,
      "Xishu": 1.0,
      "RealDevNo": 500,
      "type": 0,
      "CurrentValue": 0.0,
      "Idx": 7
    },
    {
      "No": 8,
      "Name": "设备[0]-故障停运-实时库号[501]",
      "Unit": null,
      "Addr": 9,
      "Xishu": 1.0,
      "RealDevNo": 501,
      "type": 0,
      "CurrentValue": 0.0,
      "Idx": 8
    },
    {
      "No": 9,
      "Name": "设备[0]-设备点检-实时库号[502]",
      "Unit": null,
      "Addr": 10,
      "Xishu": 1.0,
      "RealDevNo": 502,
      "type": 0,
      "CurrentValue": 0.0,
      "Idx": 9
    }
  ],
  "YKDataItem": [
    {
      "$type": "LTU.SelectedYkTable, 边缘网关维护软件",
      "Xishu": 0.0,
      "YkValue": 0,
      "No": 0,
      "Name": "设备[1]-设备自身遥控1-实时库号[70]",
      "Unit": null,
      "Addr": 24577,
      "RealDevNo": 1,
      "type": 2,
      "CurrentValue": 0.0,
      "Idx": 0
    },
    {
      "$type": "LTU.SelectedYkTable, 边缘网关维护软件",
      "Xishu": 0.0,
      "YkValue": 3,
      "No": 1,
      "Name": "设备[1]-设备自身遥控2-实时库号[71]",
      "Unit": null,
      "Addr": 24577,
      "RealDevNo": 2,
      "type": 2,
      "CurrentValue": 0.0,
      "Idx": 0
    }
  ],
  "DDDataItem": []
}
